[
    {
        "title": "2024 NEW 완전합격 제과제빵기능사 필기",
        "imageURL": "https://image.aladin.co.kr/product/33280/94/cover200/8940647998_1.jpg",
        "price": "23,400원"
    },
    {
        "title": "2024 에듀윌 제과·제빵기능사 필기끝장 (산업기사 대비가능)",
        "imageURL": "https://image.aladin.co.kr/product/32899/74/cover200/k262936625_1.jpg",
        "price": "19,800원"
    },
    {
        "title": "2024 제과제빵기능사 & 산업기사 필기",
        "imageURL": "https://image.aladin.co.kr/product/32536/7/cover200/k202935127_1.jpg",
        "price": "19,800원"
    },
    {
        "title": "2024 완전합격 제과.제빵기능사 실기",
        "imageURL": "https://image.aladin.co.kr/product/33251/50/cover200/8940648021_1.jpg",
        "price": "23,400원"
    },
    {
        "title": "2024 제과제빵기능사 필기 쪽집게 CBT 복원 기출문제집",
        "imageURL": "https://image.aladin.co.kr/product/32578/93/cover200/k732935244_1.jpg",
        "price": "16,200원"
    },
    {
        "title": "2024 이기적 제과·제빵기능사 필기+실기 환상의 콤비(산업기사 포함) (무료 체험판)",
        "imageURL": null,
        "price": "0원"
    },
    {
        "title": "2024 기분파 제과제빵기능사 필기 (통합)",
        "imageURL": "https://image.aladin.co.kr/product/32876/3/cover200/k612936113_1.jpg",
        "price": "18,000원"
    },
    {
        "title": "2024 에듀윌 제과·제빵기능사 필기끝장 (산업기사 대비가능)",
        "imageURL": null,
        "price": "17,820원"
    },
    {
        "title": "2024 제과제빵기능사 실기",
        "imageURL": "https://image.aladin.co.kr/product/32727/73/cover200/k522936979_1.jpg",
        "price": "23,400원"
    },
    {
        "title": "2024 이기적 제과·제빵기능사 필기+실기 환상의 콤비(산업기사 포함)",
        "imageURL": "https://image.aladin.co.kr/product/33527/77/cover200/8931474539_1.jpg",
        "price": "28,800원"
    },
    {
        "title": "2024 최단기 3일 완성 제과제빵기능사 총정리문제",
        "imageURL": null,
        "price": "12,600원"
    },
    {
        "title": "2024 최신판 원큐패스 제과제빵기능사 필기",
        "imageURL": "https://image.aladin.co.kr/product/32969/56/cover200/8927773179_1.jpg",
        "price": "18,000원"
    },
    {
        "title": "2024 에듀윌 제과·제빵기능사 실기끝장",
        "imageURL": "https://image.aladin.co.kr/product/33205/69/cover200/k712937953_1.jpg",
        "price": "23,400원"
    },
    {
        "title": "2024 최신판 원큐패스 합격특강 제과제빵기능사 실기",
        "imageURL": "https://image.aladin.co.kr/product/33199/38/cover200/8927773217_1.jpg",
        "price": "11,700원"
    },
    {
        "title": "제과제빵기능사 실기",
        "imageURL": "https://image.aladin.co.kr/product/33927/41/cover200/k882930035_1.jpg",
        "price": "14,000원"
    },
    {
        "title": "2024 제과제빵기능사 & 산업기사 올인원 필기",
        "imageURL": "https://image.aladin.co.kr/product/33243/47/cover200/k592938367_1.jpg",
        "price": "19,800원"
    },
    {
        "title": "제과제빵기능사 & 실무특강",
        "imageURL": "https://image.aladin.co.kr/product/33581/32/cover200/k152939494_1.jpg",
        "price": "33,000원"
    },
    {
        "title": "2024 원큐패스 제빵기능사 필기 빈출 문제 10회",
        "imageURL": "https://image.aladin.co.kr/product/32963/85/cover200/8927773195_1.jpg",
        "price": "11,700원"
    },
    {
        "title": "2024 제과제빵기능사 필기 최근기출문제",
        "imageURL": "https://image.aladin.co.kr/product/33038/76/cover200/k572937680_1.jpg",
        "price": "14,400원"
    },
    {
        "title": "2024 제과제빵기능사 필기",
        "imageURL": "https://image.aladin.co.kr/product/32977/59/cover200/k402936554_1.jpg",
        "price": "16,200원"
    },
    {
        "title": "2024 이기적 제과·제빵기능사 필기+실기 환상의 콤비(산업기사 포함)",
        "imageURL": null,
        "price": "25,600원"
    },
    {
        "title": "2024 제과제빵기능사 실기",
        "imageURL": "https://image.aladin.co.kr/product/33063/48/cover200/k692937098_1.jpg",
        "price": "18,000원"
    },
    {
        "title": "2024 최신판 원큐패스 제과제빵기능사 실기",
        "imageURL": "https://image.aladin.co.kr/product/33199/89/cover200/8927773209_1.jpg",
        "price": "21,600원"
    },
    {
        "title": "2022 제과제빵기능사 실기",
        "imageURL": null,
        "price": "30,000원"
    },
    {
        "title": "제과.제빵기능사 필기 [이론+문제]",
        "imageURL": "https://image.aladin.co.kr/product/27643/90/cover200/k512733229_1.jpg",
        "price": "18,000원"
    }
]